raw2tmap/__init__.py
raw2tmap/__main__.py
raw2tmap/raw2tmap.py
raw2tmap-0.2.0.dist-info/LICENSE
raw2tmap-0.2.0.dist-info/METADATA
raw2tmap-0.2.0.dist-info/WHEEL
raw2tmap-0.2.0.dist-info/entry_points.txt
raw2tmap-0.2.0.dist-info/top_level.txt
raw2tmap-0.2.0.dist-info/RECORD
