Metadata-Version: 2.1
Name: raw2tmap
Version: 0.2.0
Summary: Convert OME-Zarr files to TMAP format
Home-page: https://github.com/TissUUmaps/raw2tmap
Author: SciLifeLab BioImage Informatics Facility (BIIF)
Author-email: biif@scilifelab.se
License: MIT
Classifier: Operating System :: OS Independent
Classifier: Programming Language :: Python :: 3
Classifier: Programming Language :: Python :: 3.9
Classifier: Programming Language :: Python :: 3.10
Classifier: Programming Language :: Python :: 3.11
Classifier: License :: OSI Approved :: MIT License
Requires-Python: >=3.9
License-File: LICENSE
Requires-Dist: click
Requires-Dist: ome-zarr
Requires-Dist: scikit-image
Requires-Dist: tifffile
Requires-Dist: tissuumaps-schema ~=1.0
Requires-Dist: tqdm
Provides-Extra: dzi
Requires-Dist: pyvips ; extra == 'dzi'
